managesieve.py
managesieve-0.8.1.data/scripts/sieveshell
managesieve-0.8.1.dist-info/licenses/LICENSE
managesieve-0.8.1.dist-info/METADATA
managesieve-0.8.1.dist-info/WHEEL
managesieve-0.8.1.dist-info/top_level.txt
managesieve-0.8.1.dist-info/zip-safe
managesieve-0.8.1.dist-info/RECORD
