Metadata-Version: 2.4
Name: managesieve
Version: 0.8.1
Summary: RFC-5804 Manage Sieve client library for remotely managing Sieve scripts
Home-page: https://managesieve.readthedocs.io/
Download-URL: https://pypi.org/project/managesieve/
Author: Hartmut Goebel
Author-email: h.goebel@crazy-compilers.com
License: PSF-2.0 AND GPL-3.0-only
Project-URL: Documentation, https://managesieve.readthedocs.io/
Project-URL: Source Code, https://gitlab.com/htgoebel/managesieve/
Project-URL: Bug Tracker, https://gitlab.com/htgoebel/managesieve/issues
Project-URL: Funding, http://crazy-compilers.com/donate.html
Keywords: sieve,managesieve,sieveshell,RFC 5804
Platform: POSIX
Classifier: Development Status :: 5 - Production/Stable
Classifier: Environment :: Console
Classifier: Intended Audience :: End Users/Desktop
Classifier: Intended Audience :: Developers
Classifier: Natural Language :: English
Classifier: Operating System :: OS Independent
Classifier: Programming Language :: Python :: 3
Classifier: Topic :: Communications :: Email
Classifier: Topic :: Software Development :: Libraries :: Python Modules
Classifier: Topic :: Utilities
Requires-Python: >=3.6
License-File: LICENSE
Dynamic: download-url
Dynamic: license-file
